datax_split/__init__.py
datax_split/check_datax_task_status.py
datax_split/datax_to_hive_run.py
datax_split/settings.py
datax_split/tables.py
datax_split/tables_all.py
datax_split/tables_test.py
datax_split/test.py
datax_split/utils.py
datax_split-0.1.0.dist-info/LICENSE.md
datax_split-0.1.0.dist-info/METADATA
datax_split-0.1.0.dist-info/WHEEL
datax_split-0.1.0.dist-info/top_level.txt
datax_split-0.1.0.dist-info/RECORD
